{
  "archivo_sugerido": "resumen_conversacion.json",
  "fecha_contexto": "2026-07-20",
  "proyecto": {
    "nombre": "pCobra",
    "repositorio_local": "C:/Users/Adolfo/PycharmProjects/pCobra",
    "repositorio_remoto": "https://github.com/Alphonsus411/pCobra.git",
    "rama_actual": "feat/flet-0.86-editor",
    "rama_principal": "master"
  },
  "preferencias_del_usuario": {
    "idioma": "español",
    "nombre_usuario": "Adolfo",
    "asistente": "Bella",
    "formato_de_trabajo": "Presentar como máximo tres comandos o pruebas por respuesta para evitar sobrecarga.",
    "estilo": "Técnico, claro, cercano y estructurado."
  },
  "incidencia_nodo_para": {
    "estado": "resuelta, validada, fusionada y publicada",
    "problema_original": "El parser generaba NodoPara, pero el intérprete producía: Nodo no soportado: <class 'pcobra.core.ast_nodes.NodoPara'>.",
    "rama": "fix/interpreter-nodo-para",
    "commit_correccion": {
      "hash": "3e988828",
      "mensaje": "fix(runtime): ejecutar bucles para en el intérprete"
    },
    "commit_merge": {
      "hash": "ee86154d",
      "mensaje": "merge: soportar bucles para en el intérprete"
    },
    "cambios": [
      "Se importó NodoPara en src/pcobra/core/interpreter.py.",
      "Se añadió NodoPara al despachador del intérprete.",
      "Se implementó ejecutar_para.",
      "Se materializa el iterable antes de recorrerlo.",
      "Se valida que el valor sea iterable.",
      "La variable del bucle se declara o actualiza según el entorno.",
      "Se implementó soporte de romper y continuar.",
      "Se añadieron pruebas unitarias y una prueba de ejecución GUI."
    ],
    "archivos_modificados": [
      "src/pcobra/core/interpreter.py",
      "tests/gui/test_gui_runtime_execution_scope.py",
      "tests/unit/test_interpreter_para.py"
    ],
    "validacion_automatica": {
      "resultado": "28 passed, 1 warning",
      "codigo_salida": 0,
      "warning": "Advertencia no relacionada de Hypothesis sobre norecursedirs."
    },
    "validacion_manual": {
      "codigo": "para valor en [1, 2, 3]:\n    imprimir(valor)\nfin",
      "salida": [
        "1",
        "2",
        "3"
      ],
      "resultado": "correcto"
    },
    "sincronizacion": {
      "master_local": "ee86154d",
      "origin_master": "ee86154d",
      "estado": "sincronizados"
    }
  },
  "incidencia_tabulador": {
    "estado": "abierta",
    "problema": "La tecla Tab no introduce indentación en la superficie de escritura del IDLE.",
    "superficie_actual": {
      "archivo": "src/pcobra/gui/idle.py",
      "creacion": "entrada = runtime.crear_editor_codigo(ft)",
      "implementacion": "src/pcobra/gui/runtime.py",
      "control": "ft.TextField",
      "opciones": {
        "multiline": true,
        "expand": true
      }
    },
    "hallazgos_en_flet_0_28_3": {
      "version": "0.28.3",
      "TextField_selection": false,
      "TextField_cursor_position": false,
      "TextField_on_selection_change": false,
      "TextField_on_key_down": false,
      "TextField_on_keyboard_event": false,
      "Page_on_keyboard_event": true,
      "KeyboardListener": false,
      "CodeEditor": false,
      "conclusion": "Page puede detectar Tab, pero TextField no permite conocer ni modificar la posición del cursor o la selección. Un parche correcto de indentación no es viable con esa API."
    },
    "investigacion_interna": {
      "TextSelection": "Existe, pero se usa en controles de texto seleccionable y no proporciona edición de TextField.",
      "invoke_method": "Existe como transporte genérico, pero no se encontraron métodos cliente de TextField para obtener selección, mover cursor o insertar texto.",
      "controles_personalizados_en_repositorio": "No se encontró infraestructura existente.",
      "conclusion": "La solución correcta es migrar Flet y usar un editor especializado, en lugar de aplicar un parche privado y frágil."
    }
  },
  "migracion_flet": {
    "rama": "feat/flet-0.86-editor",
    "objetivo": "Actualizar Flet y reemplazar la superficie de escritura por un editor con soporte real de selección, cursor e indentación con Tab.",
    "linea_base_antes_de_actualizar": {
      "suite": [
        "tests/unit/test_gui_idle.py",
        "tests/gui",
        "tests/unit/test_cli_gui.py",
        "tests/unit/test_cli_gui_without_flet.py"
      ],
      "resultado": "140 passed, 1 warning",
      "codigo_salida": 0,
      "duracion": "1.65s"
    },
    "paquetes_instalados": {
      "flet": "0.86.1",
      "flet-code-editor": "0.86.1",
      "flet-desktop": "0.86.1",
      "msgpack": "1.2.1"
    },
    "conflictos_actuales_de_dependencias": [
      {
        "paquete": "agix 1.9.0",
        "restriccion": "flet>=0.28,<0.29",
        "conflicto": "Flet instalado es 0.86.1."
      },
      {
        "paquete": "pcobra 10.1.1",
        "restriccion": "flet>=0.28.3,!=0.29.*,<0.86",
        "conflicto": "Flet instalado es 0.86.1."
      }
    ],
    "conflicto_resuelto": {
      "paquete": "flet-desktop",
      "version_anterior": "0.28.3",
      "version_actual": "0.86.1"
    },
    "agix": {
      "version_instalada": "1.9.0",
      "ultima_version_disponible": "1.9.0",
      "uso_real_en_pcobra": [
        "src/pcobra/cobra/cli/commands/agix_cmd.py",
        "src/pcobra/ia/analizador_agix.py",
        "tests/integration/test_agix_reasoner.py",
        "tests/unit/test_analizador_agix.py",
        "tests/unit/test_cli_agix.py",
        "tests/unit/test_cli_agix_missing_dep.py"
      ],
      "observacion": "El código describe AGIX como dependencia opcional, pero pyproject.toml todavía lo declara como dependencia obligatoria.",
      "decision_provisional": "Mover AGIX a un extra opcional, por ejemplo pcobra[ai], para desacoplarlo de la GUI basada en Flet 0.86.1."
    }
  },
  "estado_de_pyproject": {
    "version_proyecto": "10.1.1",
    "python": ">=3.11",
    "dependencia_agix_actual": "agix>=1.9.0,<2",
    "dependencia_flet_actual": "flet>=0.28.3,!=0.29.*,<0.86",
    "cambios_propuestos_no_confirmados": [
      "Eliminar agix de project.dependencies.",
      "Añadir ai = [\"agix>=1.9.0,<2\"] en project.optional-dependencies.",
      "Cambiar Flet a flet[desktop]==0.86.1.",
      "Añadir flet-code-editor==0.86.1.",
      "Regenerar requirements.txt, requirements-dev.txt y docs/requirements.txt después de estabilizar la migración."
    ]
  },
  "estado_actual_confirmado": {
    "rama": "feat/flet-0.86-editor",
    "flet_instalado": "0.86.1",
    "flet_code_editor_instalado": "0.86.1",
    "flet_desktop_instalado": "0.86.1",
    "agix_instalado": "1.9.0",
    "pip_check": [
      "agix 1.9.0 es incompatible con Flet 0.86.1.",
      "Los metadatos instalados de pcobra 10.1.1 todavía restringen Flet a una versión menor que 0.86."
    ],
    "cambios_git_de_la_migracion": "No se ha confirmado todavía ningún cambio de código ni commit en esta rama.",
    "suite_gui_despues_de_actualizar": "Todavía no ejecutada, porque primero se estaba resolviendo la coherencia de dependencias."
  },
  "siguiente_secuencia_recomendada": [
    {
      "paso": 1,
      "accion": "Modificar pyproject.toml para actualizar Flet, añadir flet-code-editor y mover AGIX al extra opcional ai."
    },
    {
      "paso": 2,
      "accion": "Desinstalar AGIX del entorno GUI principal, reinstalar pCobra en modo editable y ejecutar pip check."
    },
    {
      "paso": 3,
      "accion": "Ejecutar la suite GUI para obtener el mapa real de incompatibilidades con Flet 0.86.1."
    }
  ],
  "comandos_propuestos_anteriormente_pero_no_confirmados": {
    "actualizar_pyproject": "Editar pyproject.toml para sustituir la restricción antigua de Flet, añadir flet-code-editor y mover AGIX a project.optional-dependencies.ai.",
    "limpiar_entorno": "python -m pip uninstall -y agix && python -m pip install -e . && python -m pip check",
    "medir_migracion": "python -m pytest -q tests/unit/test_gui_idle.py tests/gui tests/unit/test_cli_gui.py tests/unit/test_cli_gui_without_flet.py --tb=short"
  },
  "riesgos_y_precauciones": [
    "No asumir que CodeEditor gestiona Tab exactamente como se necesita hasta validarlo manualmente.",
    "No mezclar la migración de Flet con incidencias antiguas no relacionadas.",
    "No reinstalar pcobra[ai] junto con Flet 0.86.1 mientras AGIX mantenga su restricción flet<0.29.",
    "Mantener commits separados para dependencias, adaptación de API y sustitución del editor.",
    "Actualizar los archivos de requisitos bloqueados solo después de estabilizar pyproject.toml."
  ],
  "incidencias_independientes_detectadas": [
    {
      "archivo": "tests/unit/test_parser_consistencia_ast.py",
      "problema": "Usa la sintaxis antigua para i in x.",
      "sintaxis_actual": "para i en x"
    },
    {
      "archivo": "tests/unit/test_romper_continuar.py",
      "problema": "Contiene expectativas antiguas de parser y transpiladores."
    },
    {
      "suite": "tests/unit/test_interpreter.py",
      "problema": "Existen fallos previos no relacionados con NodoPara."
    },
    {
      "problema": "Hay una duplicación histórica potencial entre imports core.interpreter y pcobra.core.interpreter.",
      "decision": "No mezclar esta incidencia con la migración actual."
    }
  ],
  "plan_de_commits_sugerido": [
    "chore(deps): actualizar Flet y desacoplar AGIX",
    "refactor(gui): adaptar wrappers y pruebas a Flet 0.86.1",
    "feat(gui): usar CodeEditor y soportar indentación con Tab"
  ]
}